{
	"hosting": {
		"S3AndCloudFront": {
			"service": "S3AndCloudFront",
			"providerPlugin": "awscloudformation"
		}
	},
	"auth": {
		"testa149649a": {
			"service": "Cognito",
			"providerPlugin": "awscloudformation",
			"dependsOn": [],
			"customAuth": false
		}
	},
	"storage": {
		"testStorage": {
			"service": "S3",
			"providerPlugin": "awscloudformation"
		}
	},
	"api": {
		"test": {
			"service": "AppSync",
			"providerPlugin": "awscloudformation",
			"output": {
				"authConfig": {
					"additionalAuthenticationProviders": [],
					"defaultAuthentication": {
						"authenticationType": "AMAZON_COGNITO_USER_POOLS",
						"userPoolConfig": {
							"userPoolId": "authtesta149649a"
						}
					}
				}
			}
		}
	},
	"function": {
		"functest": {
			"service": "Lambda",
			"providerPlugin": "awscloudformation",
			"build": true,
			"dependsOn": [
				{
					"category": "storage",
					"resourceName": "testStorage",
					"attributes": [
						"BucketName"
					]
				},
				{
					"category": "api",
					"resourceName": "test",
					"attributes": [
						"GraphQLAPIIdOutput",
						"GraphQLAPIEndpointOutput"
					]
				}
			]
		}
	}
}